MANIFEST.in
README.rst
setup.py
docs/HISTORY.txt
docs/LICENSE.GPL
docs/LICENSE.txt
ftw/__init__.py
ftw.table.egg-info/PKG-INFO
ftw.table.egg-info/SOURCES.txt
ftw.table.egg-info/dependency_links.txt
ftw.table.egg-info/entry_points.txt
ftw.table.egg-info/namespace_packages.txt
ftw.table.egg-info/not-zip-safe
ftw.table.egg-info/requires.txt
ftw.table.egg-info/top_level.txt
ftw/table/__init__.py
ftw/table/basesource.py
ftw/table/catalog_source.py
ftw/table/column.py
ftw/table/configure.zcml
ftw/table/helper.py
ftw/table/interfaces.py
ftw/table/testing.py
ftw/table/utils.py
ftw/table/Extensions/__init__.py
ftw/table/Extensions/install.py
ftw/table/browser/__init__.py
ftw/table/browser/configure.zcml
ftw/table/browser/ftwtable.extjs.js
ftw/table/browser/jquery.ftwtable.js
ftw/table/browser/extjs/ext-all.css
ftw/table/browser/extjs/images/checked.gif
ftw/table/browser/extjs/images/col-move-bottom.gif
ftw/table/browser/extjs/images/col-move-top.gif
ftw/table/browser/extjs/images/columns.gif
ftw/table/browser/extjs/images/group-by.gif
ftw/table/browser/extjs/images/hmenu-asc.gif
ftw/table/browser/extjs/images/hmenu-desc.gif
ftw/table/browser/extjs/images/item_arrow.png
ftw/table/browser/extjs/images/mini-bottom.gif
ftw/table/browser/extjs/images/mini-top.gif
ftw/table/browser/extjs/images/sort_asc.png
ftw/table/browser/extjs/images/sort_desc.png
ftw/table/browser/extjs/images/td_menu_button.png
ftw/table/browser/extjs/images/td_menu_button_hover.png
ftw/table/browser/extjs/images/unchecked.gif
ftw/table/locales/ftw.table-manual.pot
ftw/table/locales/ftw.table.pot
ftw/table/locales/de/LC_MESSAGES/ftw.table.po
ftw/table/locales/en/LC_MESSAGES/ftw.table.po
ftw/table/locales/fr/LC_MESSAGES/ftw.table.po
ftw/table/profiles/default/jsregistry.xml
ftw/table/profiles/default/metadata.xml
ftw/table/profiles/extjs/cssregistry.xml
ftw/table/profiles/extjs/jsregistry.xml
ftw/table/profiles/extjs/metadata.xml
ftw/table/profiles/uninstall/cssregistry.xml
ftw/table/profiles/uninstall/jsregistry.xml
ftw/table/templates/basic.pt
ftw/table/tests/__init__.py
ftw/table/tests/test_catalog_source.py
ftw/table/tests/test_helper_draggable.py
ftw/table/tests/test_helper_integration_link.py
ftw/table/tests/test_helper_integration_readable_author.py
