Metadata-Version: 1.1
Name: ftw.table
Version: 1.19.1
Summary: Table generator utility for use within zope.
Home-page: https://github.com/4teamwork/ftw.table
Author: Jonas Baumann
Author-email: mailto:info@4teamwork.ch
License: GPL2
Keywords: ftw table generator
Platform: UNKNOWN
Classifier: Framework :: Plone
Classifier: Framework :: Plone :: 4.0
Classifier: Framework :: Plone :: 4.2
Classifier: Framework :: Plone :: 4.3
Classifier: Programming Language :: Python
Classifier: Topic :: Software Development :: Libraries :: Python Modules
